nessus/__init__.py
nessus/agent_groups.py
nessus/agents.py
nessus/editor.py
nessus/files.py
nessus/folders.py
nessus/groups.py
nessus/mail.py
nessus/migration.py
nessus/nessus.py
nessus/permissions.py
nessus/plugin_rules.py
nessus/plugins.py
nessus/policies.py
nessus/proxy.py
nessus/scanners.py
nessus/scans.py
nessus/server.py
nessus/session.py
nessus/settings.py
nessus/software_update.py
nessus/terrascan.py
nessus/tokens.py
nessus/users.py
nessus/utils.py
nessus/iterators/__init__.py
nessus/iterators/pagination.py
nessus/iterators/plugins.py
nessus/schema/__init__.py
nessus/schema/fields.py
nessus/schema/pagination.py
nessus/schema/scans.py
nessus/schema/settings.py
python_nessus_api-10.6.3.dist-info/LICENSE
python_nessus_api-10.6.3.dist-info/WHEEL
python_nessus_api-10.6.3.dist-info/METADATA
python_nessus_api-10.6.3.dist-info/RECORD
